{
  "applicantType": "INDIVIDUAL",
  "websiteUrl": "https://x.com/Airrsupply_?t=i7t_C5BlyQxvIU_nx3O7dw&s=09",
  "bio": "I am an airdrop activist and investor ",
  "contributionDescription": "saya akan menggunakan fitur fitur baru untuk mengetahui adanya bug atau tidak , serta memberitahu dev untuk menjadi lebih baik lagi , dan saya adalah salah satu dari pada pemeggang token op , dan token op adalah yang terbaik si menurut saya , semoga project ini akan lebih baik, good luck",
  "contributionLinks": [
    {
      "type": "CONTRACT_ADDRESS",
      "url": "https://optimistic.etherscan.io/address/0x83d972c23cca53485b3dce8508159f46550EC342",
      "description": "optimism"
    }
  ],
  "impactCategory": [
    "END_USER_EXPERIENCE_AND_ADOPTION"
  ],
  "impactDescription": "berkat saya test jaringannya , developer jadi tau appa saja yang harus perlu di perbaikin , sejauh ini cukup baik yaa , mungkin lebih di perhatikaann lagi agar dapat hasil yang maksimal dan selain itu juga saya adalah holder dari token op yang dimana akan membuat harganya lebih baik lagi , termakasih",
  "impactMetrics": [
    {
      "description": "binance#123",
      "number": 5665,
      "url": "https://optimistic.etherscan.io/address/0x83d972c23cca53485b3dce8508159f46550EC342"
    }
  ],
  "fundingSources": [],
  "payoutAddress": "0x83d972c23cca53485b3dce8508159f46550EC342",
  "understoodKYCRequirements": true,
  "understoodFundClaimPeriod": true,
  "certifiedNotDesignatedOrSanctionedOrBlocked": true,
  "certifiedNotSponsoredByPoliticalFigureOrGovernmentEntity": true,
  "certifiedNotBarredFromParticipating": true,
  "displayName": "akunotwin",
  "applicantName": "akunotwin",
  "applicationMetadataPtr": "https://content.optimism.io/rpgf3Application/v0/metadata/10/0x83d972c23cca53485b3dce8508159f46550EC342.json",
  "RPGF3_Application_UID": "0xb1193e30684a9b00f4bad3a94da7c4d3cb0660dff088e3d4efd4a9a3bdc4a273",
  "applicantAddress": "0x83d972c23cca53485b3dce8508159f46550EC342",
  "pwIsFlagged": true,
  "pwFlaggedReason": "The application should be flagged for being in a language other than English.",
  "pwApplicantTypeChecked": true
}